<?xml version="1.0" encoding="UTF-8"?>
<OAI-PMH xmlns="http://www.openarchives.org/OAI/2.0/" xmlns:xsi="http://www.w3.org/2001/XMLSchema-instance" xsi:schemaLocation="http://www.openarchives.org/OAI/2.0/ http://www.openarchives.org/OAI/2.0/OAI-PMH.xsd">
<responseDate>2015-04-08T22:11:58Z</responseDate>
<request verb="ListRecords" until="2012-03-15" from="2012-03-01" metadataPrefix="arXiv">http://export.arxiv.org/oai2</request>
<ListRecords>
<record>
<header>
 <identifier>oai:arXiv.org:0704.0073</identifier>
 <datestamp>2012-03-06</datestamp>
 <setSpec>math</setSpec>
</header>
<metadata>
 <arXiv xmlns="http://arxiv.org/OAI/arXiv/" xmlns:xsi="http://www.w3.org/2001/XMLSchema-instance" xsi:schemaLocation="http://arxiv.org/OAI/arXiv/ http://arxiv.org/OAI/arXiv.xsd">
 <id>0704.0073</id><created>2007-04-01</created><updated>2012-03-04</updated><authors><author><keyname>Fujino</keyname><forenames>Osamu</forenames></author></authors><title>A transcendental approach to Koll\'ar's injectivity theorem</title><categories>math.AG</categories><comments>22 pages; a minor revision of the preprint circulated in January
  2006, v2: minor modifications, v3: final version, to appear in Osaka J. Math</comments><msc-class>32L10, 32W05</msc-class><license>http://arxiv.org/licenses/nonexclusive-distrib/1.0/</license><abstract>  We treat Koll\'ar's injectivity theorem from the analytic (or differential
geometric) viewpoint. More precisely, we give a curvature condition which
implies Koll\'ar type cohomology injectivity theorems. Our main theorem is
formulated for a compact K\&quot;ahler manifold, but the proof uses the space of
harmonic forms on a Zariski open set with a suitable complete K\&quot;ahler metric.
We need neither covering tricks, desingularizations, nor Leray's spectral
sequence.
</abstract></arXiv>
</metadata>
</record>
<record>
<header>
 <identifier>oai:arXiv.org:0704.0498</identifier>
 <datestamp>2012-03-01</datestamp>
 <setSpec>physics:hep-ex</setSpec>
</header>
<metadata>
 <arXiv xmlns="http://arxiv.org/OAI/arXiv/" xmlns:xsi="http://www.w3.org/2001/XMLSchema-instance" xsi:schemaLocation="http://arxiv.org/OAI/arXiv/ http://arxiv.org/OAI/arXiv.xsd">
 <id>0704.0498</id><created>2007-04-04</created><updated>2007-12-05</updated><authors><author><keyname>Mention</keyname><forenames>Guillaume</forenames><affiliation>DAPNIA</affiliation></author><author><keyname>Lasserre</keyname><forenames>Thierry</forenames><affiliation>DAPNIA, APC</affiliation></author><author><keyname>Motta</keyname><forenames>Dario</forenames><affiliation>DAPNIA</affiliation></author></authors><title>A unified analysis of the reactor neutrino program towards the
  measurement of the theta_13 mixing angle</title><categories>hep-ex</categories><comments>28 pages, 7 figures, 14 tables, one appendix</comments><proxy>ccsd hal-00139903</proxy><journal-ref>Journal of Physics: Conference Series 110, 8 (2008) 082013</journal-ref><doi>10.1088/1742-6596/110/8/082013</doi><abstract>  We present in this article a detailed quantitative discussion of the
measurement of the leptonic mixing angle theta_13 through currently scheduled
reactor neutrino oscillation experiments. We thus focus on Double Chooz (Phase
I &amp; II), Daya Bay (Phase I &amp; II) and RENO experiments. We perform a unified
analysis, including systematics, backgrounds and accurate experimental setup in
each case. Each identified systematic error and background impact has been
assessed on experimental setups following published data when available and
extrapolating from Double Chooz acquired knowledge otherwise. After reviewing
the experiments, we present a new analysis of their sensitivities to sin^2(2
theta_13) and study the impact of the different systematics based on the pulls
approach. Through this generic statistical analysis we discuss the advantages
and drawbacks of each experimental setup.
</abstract></arXiv>
</metadata>
</record>
<record>
<header>
 <identifier>oai:arXiv.org:0704.3093</identifier>
 <datestamp>2012-03-01</datestamp>
 <setSpec>math</setSpec>
</header>
<metadata>
 <arXiv xmlns="http://arxiv.org/OAI/arXiv/" xmlns:xsi="http://www.w3.org/2001/XMLSchema-instance" xsi:schemaLocation="http://arxiv.org/OAI/arXiv/ http://arxiv.org/OAI/arXiv.xsd">
 <id>0704.3093</id><created>2007-04-23</created><updated>2012-02-29</updated><authors><author><keyname>Meilhan</keyname><forenames>Jean-Baptiste</forenames></author><author><keyname>Yasuhara</keyname><forenames>Akira</forenames></author></authors><title>Whitehead double and Milnor invariants</title><categories>math.GT</categories><comments>9 pages, 5 figures. Some minor modifications in this final version</comments><msc-class>57M25, 57M27</msc-class><journal-ref>Osaka J. Math. 48 No. 2 (2011), 371-381</journal-ref><license>http://arxiv.org/licenses/nonexclusive-distrib/1.0/</license><abstract>  We consider the operation of Whitehead double on a component of a link and
study the behavior of Milnor invariants under this operation. We show that this
operation turns a link whose Milnor invariants of length &lt; k are all zero into
a link with vanishing Milnor invariants of length &lt; 2k, and we provide formulas
for the first non-vanishing ones.
  As a consequence, we obtain statements relating the notions of link-homotopy
and self Delta-equivalence via the Whitehead double operation. By using our
result, we show that a Brunnian link L is link-homotopic to the unlink if and
only if a link L with a single component Whitehed doubled is self
Delta-equivalent to the unlink.
</abstract></arXiv>
</metadata>
</record>
<record>
<header>
 <identifier>oai:arXiv.org:0705.1199</identifier>
 <datestamp>2012-03-06</datestamp>
 <setSpec>math</setSpec>
</header>
<metadata>
 <arXiv xmlns="http://arxiv.org/OAI/arXiv/" xmlns:xsi="http://www.w3.org/2001/XMLSchema-instance" xsi:schemaLocation="http://arxiv.org/OAI/arXiv/ http://arxiv.org/OAI/arXiv.xsd">
 <id>0705.1199</id><created>2007-05-08</created><updated>2012-03-04</updated><authors><author><keyname>Fujino</keyname><forenames>Osamu</forenames></author></authors><title>A transcendental approach to Koll\'ar's injectivity theorem II</title><categories>math.AG math.CV</categories><comments>30 pages, v2: added many corollaries, v3: minor modifications, v4:
  minor revision following referee's comments</comments><msc-class>32L10, 32W05</msc-class><license>http://arxiv.org/licenses/nonexclusive-distrib/1.0/</license><abstract>  We treat a relative version of the main theorem in my previous paper: A
transcendental approach to Koll\'ar's injectivity theorem. More explicitly, we
give a curvature condition that implies Koll\'ar type cohomology injectivity
theorems in the relative setting. To carry out this generalization, we use the
Ohsawa-Takegoshi twisted version of Nakano's identity.
</abstract></arXiv>
</metadata>
</record>
<record>
<header>
 <identifier>oai:arXiv.org:0705.1487</identifier>
 <datestamp>2012-03-02</datestamp>
 <setSpec>math</setSpec>
</header>
<metadata>
 <arXiv xmlns="http://arxiv.org/OAI/arXiv/" xmlns:xsi="http://www.w3.org/2001/XMLSchema-instance" xsi:schemaLocation="http://arxiv.org/OAI/arXiv/ http://arxiv.org/OAI/arXiv.xsd">
 <id>0705.1487</id><created>2007-05-10</created><authors><author><keyname>Bandieri</keyname><forenames>Paola</forenames></author><author><keyname>Cristofori</keyname><forenames>Paola</forenames></author><author><keyname>Gagliardi</keyname><forenames>Carlo</forenames></author></authors><title>Nonorientable 3-manifolds admitting coloured triangulations with at most
  30 tetrahedra</title><categories>math.GT</categories><comments>18 pages, 3 figures</comments><msc-class>57Q15, 57M15, 57N10</msc-class><journal-ref>Journal of Knot Theory and its Ramifications 18 (3) (2009),
  381-395</journal-ref><abstract>  We present the census of all non-orientable, closed, connected 3-manifolds
admitting a rigid crystallization with at most 30 vertices. In order to obtain
the above result, we generate, manipulate and compare, by suitable computer
procedures, all rigid non-bipartite crystallizations up to 30 vertices.
</abstract></arXiv>
</metadata>
</record>
<record>
<header>
 <identifier>oai:arXiv.org:0705.3667</identifier>
 <datestamp>2012-03-06</datestamp>
 <setSpec>math</setSpec>
</header>
<metadata>
 <arXiv xmlns="http://arxiv.org/OAI/arXiv/" xmlns:xsi="http://www.w3.org/2001/XMLSchema-instance" xsi:schemaLocation="http://arxiv.org/OAI/arXiv/ http://arxiv.org/OAI/arXiv.xsd">
 <id>0705.3667</id><created>2007-05-24</created><updated>2012-03-05</updated><authors><author><keyname>Daskalopoulos</keyname><forenames>Panagiota</forenames></author><author><keyname>Sesum</keyname><forenames>Natasa</forenames></author></authors><title>Classification of singularities in the complete conformally flat Yamabe
  flow</title><categories>math.DG</categories><comments>The paper has been withdrawn due to a crucial error in the argument</comments><msc-class>53C44</msc-class><license>http://arxiv.org/licenses/nonexclusive-distrib/1.0/</license><abstract>  We show that an eternal solution to a complete, locally conformally flat
Yamabe flow, $\frac{\partial}{\partial t} g = -Rg$, with uniformly bounded
scalar curvature and positive Ricci curvature at $t = 0$, where the scalar
curvature assumes its maximum is a gradient steady soliton. As an application
of that, we study the blow up behavior of $g(t)$ at the maximal time of
existence, $T &lt; \infty$. We assume that $(M,g(\cdot, t))$ satisfies (i) the
injectivity radius bound {\bf or} (ii) the Schouten tensor is positive at time
$t = 0$ and the scalar curvature bounded at each time-slice. We show that the
singularity the flow develops at time $T$ is always of type I.
</abstract></arXiv>
</metadata>
</record>
<record>
<header>
 <identifier>oai:arXiv.org:0705.4548</identifier>
 <datestamp>2012-03-01</datestamp>
 <setSpec>math</setSpec>
 <setSpec>physics:quant-ph</setSpec>
</header>
<metadata>
 <arXiv xmlns="http://arxiv.org/OAI/arXiv/" xmlns:xsi="http://www.w3.org/2001/XMLSchema-instance" xsi:schemaLocation="http://arxiv.org/OAI/arXiv/ http://arxiv.org/OAI/arXiv.xsd">
 <id>0705.4548</id><created>2007-05-31</created><updated>2011-02-11</updated><authors><author><keyname>Loebl</keyname><forenames>Martin</forenames></author><author><keyname>Moffatt</keyname><forenames>Iain</forenames></author></authors><title>A permanent formula for the Jones polynomial</title><categories>math.QA math.CO quant-ph</categories><comments>To appear in Advances in Applied Mathematics</comments><journal-ref>Adv. in Appl. Math., 47 (2011) 659-667</journal-ref><doi>10.1016/j.aam.2011.03.003</doi><license>http://arxiv.org/licenses/nonexclusive-distrib/1.0/</license><abstract>  The permanent of a square matrix is defined in a way similar to the
determinant, but without using signs. The exact computation of the permanent is
hard, but there are Monte-Carlo algorithms that can estimate general
permanents. Given a planar diagram of a link L with $n$ crossings, we define a
7n by 7n matrix whose permanent equals to the Jones polynomial of L. This
result accompanied with recent work of Freedman, Kitaev, Larson and Wang
provides a Monte-Carlo algorithm to any decision problem belonging to the class
BQP, i.e. such that it can be computed with bounded error in polynomial time
using quantum resources.
</abstract></arXiv>
</metadata>
</record>
<record>
<header>
 <identifier>oai:arXiv.org:0705.4684</identifier>
 <datestamp>2012-03-12</datestamp>
 <setSpec>physics:cond-mat</setSpec>
</header>
<metadata>
 <arXiv xmlns="http://arxiv.org/OAI/arXiv/" xmlns:xsi="http://www.w3.org/2001/XMLSchema-instance" xsi:schemaLocation="http://arxiv.org/OAI/arXiv/ http://arxiv.org/OAI/arXiv.xsd">
 <id>0705.4684</id><created>2007-05-31</created><updated>2007-06-27</updated><authors><author><keyname>Cooper</keyname><forenames>Valentino R.</forenames></author><author><keyname>Johnston</keyname><forenames>Karen</forenames></author><author><keyname>Rabe</keyname><forenames>Karin M.</forenames></author></authors><title>Polarization Enhancement in Short Period Superlattices via Interfacial
  Intermixing</title><categories>cond-mat.mtrl-sci</categories><comments>4 pages, 6 figures</comments><journal-ref>PRB 76, 020103 (R) (2007)</journal-ref><doi>10.1103/PhysRevB.76.020103</doi><abstract>  The effect of intermixing at the interface of short period
PbTiO$_3$/SrTiO$_3$ superlattices is studied using first-principles density
functional theory. The results indicate that interfacial intermixing
significantly enhances the polarization within the superlattice. This
enhancement is directly related to the off-centering of Pb and Sr cations and
can be explained through a discussion of interacting dipoles. This picture
should be general for a wide range of multicomponent superlattices and may have
important consequences for the design of ferroelectric devices.
</abstract></arXiv>
</metadata>
</record>
<record>
<header>
 <identifier>oai:arXiv.org:0707.1868</identifier>
 <datestamp>2012-03-08</datestamp>
 <setSpec>physics:cond-mat</setSpec>
</header>
<metadata>
 <arXiv xmlns="http://arxiv.org/OAI/arXiv/" xmlns:xsi="http://www.w3.org/2001/XMLSchema-instance" xsi:schemaLocation="http://arxiv.org/OAI/arXiv/ http://arxiv.org/OAI/arXiv.xsd">
 <id>0707.1868</id><created>2007-07-12</created><updated>2007-07-12</updated><authors><author><keyname>Bester</keyname><forenames>G.</forenames></author><author><keyname>Reuter</keyname><forenames>D.</forenames></author><author><keyname>He</keyname><forenames>L.</forenames></author><author><keyname>Zunger</keyname><forenames>A.</forenames></author><author><keyname>Kailuweit</keyname><forenames>P.</forenames></author><author><keyname>Wieck</keyname><forenames>A. D.</forenames></author><author><keyname>Zeitler</keyname><forenames>U.</forenames></author><author><keyname>Maan</keyname><forenames>J. C.</forenames></author><author><keyname>Wibbelhoff</keyname><forenames>O.</forenames></author><author><keyname>Lorke</keyname><forenames>A.</forenames></author></authors><title>Experimental imaging and atomistic modeling of electron and hole
  quasiparticle wave functions in InAs/GaAs quantum dots</title><categories>cond-mat.mtrl-sci</categories><comments>Submitted to Physical Review B. A version of this paper with figures
  can be found at http://www.sst.nrel.gov/nano_pub/mts_preprint.pdf</comments><journal-ref>Phys. Rev. B 76, 075338 (2007)</journal-ref><doi>10.1103/PhysRevB.76.075338</doi><abstract>  We present experimental magnetotunneling results and atomistic
pseudopotential calculations of quasiparticle electron and hole wave functions
of self-assembled InAs/GaAs quantum dots. The combination of a predictive
theory along with the experimental results allows us to gain direct insight
into the quantum states. We monitor the effects of (i) correlations, (ii)
atomistic symmetry and (iii) piezoelectricity on the confined carriers and (iv)
observe a peculiar charging sequence of holes that violates the Aufbau
principle.
</abstract></arXiv>
</metadata>
</record>
<record>
<header>
 <identifier>oai:arXiv.org:0707.2147</identifier>
 <datestamp>2012-03-14</datestamp>
 <setSpec>math</setSpec>
 <setSpec>physics:math-ph</setSpec>
</header>
<metadata>
 <arXiv xmlns="http://arxiv.org/OAI/arXiv/" xmlns:xsi="http://www.w3.org/2001/XMLSchema-instance" xsi:schemaLocation="http://arxiv.org/OAI/arXiv/ http://arxiv.org/OAI/arXiv.xsd">
 <id>0707.2147</id><created>2007-07-14</created><updated>2008-04-22</updated><authors><author><keyname>Fagnola</keyname><forenames>Franco</forenames></author><author><keyname>Umanita</keyname><forenames>Veronica</forenames></author></authors><title>Generators of Detailed Balance Quantum Markov Semigroups</title><categories>math-ph math.MP</categories><comments>31 pages</comments><msc-class>46L55, 47D05, 82B10, 82C10, 81S25</msc-class><journal-ref>Infin. Dimens. Anal. Quantum Probab. Relat. Top. 10 (3) 2007,
  335-363</journal-ref><doi>10.1142/S0219025707002762</doi><abstract>  For a quantum Markov semigroup $\T$ on the algebra $\B$ with a faithful
invariant state $\rho$, we can define an adjoint $\widetilde{\T}$ with respect
to the scalar product determined by $\rho$. In this paper, we solve the open
problems of characterising adjoints $\widetilde{\T}$ that are also a quantum
Markov semigroup and satisfy the detailed balance condition in terms of the
operators $H,L_k$ in the Gorini Kossakowski Sudarshan Lindblad representation
$\Ll(x)=i[H,x] - {1/2}\sum_k(L^*_kL_k x-2L^*_kxL_k + xL^*_kL_k)$ of the
generator of $\T$. We study the adjoint semigroup with respect to both scalar
products $&lt;a,b&gt; = \tr(\rho a^* b)$ and $&lt;a,b&gt; = \tr(\rho^{1/2} a^*
\rho^{1/2}b)$.
</abstract></arXiv>
</metadata>
</record>
</ListRecords>
</OAI-PMH>
