<OAI-PMH xmlns="http://www.openarchives.org/OAI/2.0/" xmlns:xsi="http://www.w3.org/2001/XMLSchema-instance"
         xsi:schemaLocation="http://www.openarchives.org/OAI/2.0/ http://www.openarchives.org/OAI/2.0/OAI-PMH.xsd">
    <responseDate>2016-10-04T23:44:39Z</responseDate>
    <request verb="ListRecords" metadataPrefix="stash_wrapper">http://merritt.cdlib.org/oai/v2</request>
    <ListRecords>
        <record>
            <header>
                <identifier>http://n2t.net/ark:/99999/fk43f5119b</identifier>
                <datestamp>2016-08-25T22:02:28Z</datestamp>
                <setSpec>dash_cdl</setSpec>
            </header>
            <metadata>
                <st:stash_wrapper xmlns:st="https://dash.ucop.edu/stash_wrapper/"
                                  xmlns:xsi="http://www.w3.org/2001/XMLSchema-instance"
                                  xsi:schemaLocation="https://dash.ucop.edu/stash_wrapper/ https://dash.ucop.edu/stash_wrapper/stash_wrapper.xsd">
                    <st:identifier xmlns:st="https://dash.ucop.edu/stash_wrapper/" type="DOI">10.14749/1407399498
                    </st:identifier>
                    <st:stash_administrative xmlns:st="https://dash.ucop.edu/stash_wrapper/">
                        <st:version xmlns:st="https://dash.ucop.edu/stash_wrapper/">
                            <st:version_number xmlns:st="https://dash.ucop.edu/stash_wrapper/">2</st:version_number>
                            <st:date xmlns:st="https://dash.ucop.edu/stash_wrapper/">2016-08-26Z</st:date>
                            <st:note xmlns:st="https://dash.ucop.edu/stash_wrapper/">Sample wrapped Datacite document
                            </st:note>
                        </st:version>
                        <st:license xmlns:st="https://dash.ucop.edu/stash_wrapper/">
                            <st:name xmlns:st="https://dash.ucop.edu/stash_wrapper/">Creative Commons Attribution 4.0
                                International (CC BY 4.0)
                            </st:name>
                            <st:uri xmlns:st="https://dash.ucop.edu/stash_wrapper/">
                                https://creativecommons.org/licenses/by/4.0/
                            </st:uri>
                        </st:license>
                        <st:embargo xmlns:st="https://dash.ucop.edu/stash_wrapper/">
                            <st:type xmlns:st="https://dash.ucop.edu/stash_wrapper/">none</st:type>
                            <st:period xmlns:st="https://dash.ucop.edu/stash_wrapper/">none</st:period>
                            <st:start xmlns:st="https://dash.ucop.edu/stash_wrapper/">2016-08-26Z</st:start>
                            <st:end xmlns:st="https://dash.ucop.edu/stash_wrapper/">2016-08-26Z</st:end>
                        </st:embargo>
                        <st:inventory xmlns:st="https://dash.ucop.edu/stash_wrapper/" num_files="3">
                            <st:file xmlns:st="https://dash.ucop.edu/stash_wrapper/">
                                <st:pathname xmlns:st="https://dash.ucop.edu/stash_wrapper/">1.txt</st:pathname>
                                <st:size xmlns:st="https://dash.ucop.edu/stash_wrapper/" unit="B">1</st:size>
                                <st:mime_type xmlns:st="https://dash.ucop.edu/stash_wrapper/">text/plain</st:mime_type>
                            </st:file>
                            <st:file xmlns:st="https://dash.ucop.edu/stash_wrapper/">
                                <st:pathname xmlns:st="https://dash.ucop.edu/stash_wrapper/">2.txt</st:pathname>
                                <st:size xmlns:st="https://dash.ucop.edu/stash_wrapper/" unit="B">1</st:size>
                                <st:mime_type xmlns:st="https://dash.ucop.edu/stash_wrapper/">text/plain</st:mime_type>
                            </st:file>
                            <st:file xmlns:st="https://dash.ucop.edu/stash_wrapper/">
                                <st:pathname xmlns:st="https://dash.ucop.edu/stash_wrapper/">4.txt</st:pathname>
                                <st:size xmlns:st="https://dash.ucop.edu/stash_wrapper/" unit="B">1</st:size>
                                <st:mime_type xmlns:st="https://dash.ucop.edu/stash_wrapper/">text/plain</st:mime_type>
                            </st:file>
                        </st:inventory>
                    </st:stash_administrative>
                    <st:stash_descriptive xmlns:st="https://dash.ucop.edu/stash_wrapper/">
                        <resource xmlns="http://datacite.org/schema/kernel-3"
                                  xmlns:xsi="http://www.w3.org/2001/XMLSchema-instance"
                                  xsi:schemaLocation="http://datacite.org/schema/kernel-3 http://schema.datacite.org/meta/kernel-3/metadata.xsd">
                            <identifier xmlns="http://datacite.org/schema/kernel-3" identifierType="DOI">
                                10.5072/FK23T9K69G
                            </identifier>
                            <creators xmlns="http://datacite.org/schema/kernel-3">
                                <creator xmlns="http://datacite.org/schema/kernel-3">
                                    <creatorName xmlns="http://datacite.org/schema/kernel-3">Jones, Wallace
                                    </creatorName>
                                </creator>
                                <creator xmlns="http://datacite.org/schema/kernel-3">
                                    <creatorName xmlns="http://datacite.org/schema/kernel-3">Targeta, Marketa
                                    </creatorName>
                                </creator>
                            </creators>
                            <titles xmlns="http://datacite.org/schema/kernel-3">
                                <title xmlns="http://datacite.org/schema/kernel-3"
                                       xmlns:xml="http://www.w3.org/XML/1998/namespace" xml:lang="en">Comparing the
                                    UNIVAC Computer and Sensor Networks with BEWIG
                                </title>
                            </titles>
                            <publisher xmlns="http://datacite.org/schema/kernel-3">University of California, Office of
                                the President
                            </publisher>
                            <publicationYear xmlns="http://datacite.org/schema/kernel-3">2016</publicationYear>
                            <language xmlns="http://datacite.org/schema/kernel-3">en</language>
                            <resourceType xmlns="http://datacite.org/schema/kernel-3" resourceTypeGeneral="Dataset"/>
                            <version xmlns="http://datacite.org/schema/kernel-3">2</version>
                            <descriptions xmlns="http://datacite.org/schema/kernel-3">
                                <description xmlns="http://datacite.org/schema/kernel-3"
                                             xmlns:xml="http://www.w3.org/XML/1998/namespace" xml:lang="en"
                                             descriptionType="Abstract">
                                    Interactive models and telephony [9] have garnered profound interest
                                    from both system administrators and theorists in the last several
                                    years. In our research, we disprove the analysis of context-free
                                    grammar. In this work we propose an algorithm for kernels (BEWIG),
                                    verifying that consistent hashing and Byzantine fault tolerance can
                                    collaborate to achieve this purpose.
                                </description>
                                <description xmlns="http://datacite.org/schema/kernel-3"
                                             xmlns:xml="http://www.w3.org/XML/1998/namespace" xml:lang="en"
                                             descriptionType="Methods"/>
                                <description xmlns="http://datacite.org/schema/kernel-3"
                                             xmlns:xml="http://www.w3.org/XML/1998/namespace" xml:lang="en"
                                             descriptionType="Other"/>
                            </descriptions>
                        </resource>
                    </st:stash_descriptive>
                </st:stash_wrapper>
            </metadata>
        </record>
        <record>
            <header>
                <identifier>http://n2t.net/ark:/99999/fk47s7z805</identifier>
                <datestamp>2016-09-22T16:52:38Z</datestamp>
                <setSpec>dash_ucb</setSpec>
            </header>
            <metadata>
                <st:stash_wrapper xmlns:st="https://dash.ucop.edu/stash_wrapper/"
                                  xmlns:xsi="http://www.w3.org/2001/XMLSchema-instance"
                                  xsi:schemaLocation="https://dash.ucop.edu/stash_wrapper/ https://dash.ucop.edu/stash_wrapper/stash_wrapper.xsd">
                    <st:identifier xmlns:st="https://dash.ucop.edu/stash_wrapper/" type="DOI">10.14749/1407399498
                    </st:identifier>
                    <st:stash_administrative xmlns:st="https://dash.ucop.edu/stash_wrapper/">
                        <st:version xmlns:st="https://dash.ucop.edu/stash_wrapper/">
                            <st:version_number xmlns:st="https://dash.ucop.edu/stash_wrapper/">1</st:version_number>
                            <st:date xmlns:st="https://dash.ucop.edu/stash_wrapper/">2016-09-23Z</st:date>
                            <st:note xmlns:st="https://dash.ucop.edu/stash_wrapper/">Sample wrapped Datacite document
                            </st:note>
                        </st:version>
                        <st:license xmlns:st="https://dash.ucop.edu/stash_wrapper/">
                            <st:name xmlns:st="https://dash.ucop.edu/stash_wrapper/">Creative Commons Attribution 4.0
                                International (CC BY 4.0)
                            </st:name>
                            <st:uri xmlns:st="https://dash.ucop.edu/stash_wrapper/">
                                https://creativecommons.org/licenses/by/4.0/
                            </st:uri>
                        </st:license>
                        <st:embargo xmlns:st="https://dash.ucop.edu/stash_wrapper/">
                            <st:type xmlns:st="https://dash.ucop.edu/stash_wrapper/">none</st:type>
                            <st:period xmlns:st="https://dash.ucop.edu/stash_wrapper/">none</st:period>
                            <st:start xmlns:st="https://dash.ucop.edu/stash_wrapper/">2016-09-23Z</st:start>
                            <st:end xmlns:st="https://dash.ucop.edu/stash_wrapper/">2016-09-23Z</st:end>
                        </st:embargo>
                        <st:inventory xmlns:st="https://dash.ucop.edu/stash_wrapper/" num_files="1">
                            <st:file xmlns:st="https://dash.ucop.edu/stash_wrapper/">
                                <st:pathname xmlns:st="https://dash.ucop.edu/stash_wrapper/">4.txt</st:pathname>
                                <st:size xmlns:st="https://dash.ucop.edu/stash_wrapper/" unit="B">1</st:size>
                                <st:mime_type xmlns:st="https://dash.ucop.edu/stash_wrapper/">text/plain</st:mime_type>
                            </st:file>
                        </st:inventory>
                    </st:stash_administrative>
                    <st:stash_descriptive xmlns:st="https://dash.ucop.edu/stash_wrapper/">
                        <resource xmlns="http://datacite.org/schema/kernel-3"
                                  xmlns:xsi="http://www.w3.org/2001/XMLSchema-instance"
                                  xsi:schemaLocation="http://datacite.org/schema/kernel-3 http://schema.datacite.org/meta/kernel-3/metadata.xsd">
                            <identifier xmlns="http://datacite.org/schema/kernel-3" identifierType="DOI">
                                10.5072/FK25H7HW64
                            </identifier>
                            <creators xmlns="http://datacite.org/schema/kernel-3">
                                <creator xmlns="http://datacite.org/schema/kernel-3">
                                    <creatorName xmlns="http://datacite.org/schema/kernel-3">McMullin, Gloria
                                    </creatorName>
                                </creator>
                            </creators>
                            <titles xmlns="http://datacite.org/schema/kernel-3">
                                <title xmlns="http://datacite.org/schema/kernel-3"
                                       xmlns:xml="http://www.w3.org/XML/1998/namespace" xml:lang="en">Authoring Software
                                    Considered Harmful
                                </title>
                            </titles>
                            <publisher xmlns="http://datacite.org/schema/kernel-3">University of California, Berkeley
                            </publisher>
                            <publicationYear xmlns="http://datacite.org/schema/kernel-3">2016</publicationYear>
                            <language xmlns="http://datacite.org/schema/kernel-3">en</language>
                            <resourceType xmlns="http://datacite.org/schema/kernel-3" resourceTypeGeneral="Dataset"/>
                            <version xmlns="http://datacite.org/schema/kernel-3">1</version>
                            <descriptions xmlns="http://datacite.org/schema/kernel-3">
                                <description xmlns="http://datacite.org/schema/kernel-3"
                                             xmlns:xml="http://www.w3.org/XML/1998/namespace" xml:lang="en"
                                             descriptionType="Abstract">Authoring software isn't your friend.
                                </description>
                                <description xmlns="http://datacite.org/schema/kernel-3"
                                             xmlns:xml="http://www.w3.org/XML/1998/namespace" xml:lang="en"
                                             descriptionType="Methods"/>
                                <description xmlns="http://datacite.org/schema/kernel-3"
                                             xmlns:xml="http://www.w3.org/XML/1998/namespace" xml:lang="en"
                                             descriptionType="Other"/>
                            </descriptions>
                            <geoLocations xmlns="http://datacite.org/schema/kernel-3">
                                <geoLocation xmlns="http://datacite.org/schema/kernel-3">
                                    <geoLocationPoint xmlns="http://datacite.org/schema/kernel-3">37.0 -122.0
                                    </geoLocationPoint>
                                </geoLocation>
                                <geoLocation xmlns="http://datacite.org/schema/kernel-3">
                                    <geoLocationPoint xmlns="http://datacite.org/schema/kernel-3">36.844461
                                        -120.695801
                                    </geoLocationPoint>
                                </geoLocation>
                                <geoLocation xmlns="http://datacite.org/schema/kernel-3">
                                    <geoLocationBox xmlns="http://datacite.org/schema/kernel-3">37.0 -123.0 38.0
                                        -122.0
                                    </geoLocationBox>
                                </geoLocation>
                                <geoLocation xmlns="http://datacite.org/schema/kernel-3">
                                    <geoLocationBox xmlns="http://datacite.org/schema/kernel-3">37.230328 -121.989441
                                        37.453057 -121.593933
                                    </geoLocationBox>
                                </geoLocation>
                            </geoLocations>
                        </resource>
                    </st:stash_descriptive>
                </st:stash_wrapper>
            </metadata>
        </record>
    </ListRecords>
</OAI-PMH>
